compadre
