Metadata-Version: 2.1
Name: compadre
Version: 1.0.15
Summary: Compatible Particle Discretization and Remap
Home-page: https://github.com/SNLComputation/compadre
Author: Paul Kuberry
Author-email: pkuberry@gmail.com
License: UNKNOWN
Platform: UNKNOWN
Classifier: Programming Language :: Python :: 3
Classifier: License :: OSI Approved :: BSD License
Classifier: Operating System :: Unix
